awsgnssroutils/__init__.py
awsgnssroutils/database.py
awsgnssroutils/collocation/__init__.py
awsgnssroutils/collocation/rotcol.py
awsgnssroutils/collocation/core/__init__.py
awsgnssroutils/collocation/core/awsro.py
awsgnssroutils/collocation/core/brute_force.py
awsgnssroutils/collocation/core/celestrak.py
awsgnssroutils/collocation/core/collocation.py
awsgnssroutils/collocation/core/constants_and_utils.py
awsgnssroutils/collocation/core/eumetsat.py
awsgnssroutils/collocation/core/nadir_satellite.py
awsgnssroutils/collocation/core/nasa_earthdata.py
awsgnssroutils/collocation/core/noaa.py.dev
awsgnssroutils/collocation/core/rotation_collocation.py
awsgnssroutils/collocation/core/spacetrack.py
awsgnssroutils/collocation/core/timestandards.py
awsgnssroutils/collocation/instruments/__init__.py
awsgnssroutils/collocation/instruments/airs.py
awsgnssroutils/collocation/instruments/amsua.py
awsgnssroutils/collocation/instruments/atms.py
awsgnssroutils-1.2.6.dist-info/METADATA
awsgnssroutils-1.2.6.dist-info/WHEEL
awsgnssroutils-1.2.6.dist-info/entry_points.txt
awsgnssroutils-1.2.6.dist-info/licenses/LICENSE
awsgnssroutils-1.2.6.dist-info/RECORD
