Metadata-Version: 2.4
Name: awsgnssroutils
Version: 1.2.6
Summary: Utilities for access and manipulation of GNSS radio occultation in the AWS Registry of Open Data
Project-URL: Homepage, https://github.com/gnss-ro/aws-opendata/tree/master/awsgnssroutils
Project-URL: Bug Tracker, https://github.com/gnss-ro/aws-opendata/issues
Author-email: Stephen Leroy <sleroy@aer.com>, Amy McVey <amcvey@aer.com>
License-File: LICENSE
Classifier: License :: OSI Approved :: BSD License
Classifier: Operating System :: OS Independent
Classifier: Programming Language :: Python :: 3
Requires-Python: >=3.9
Requires-Dist: aiobotocore[awscli,boto3]
Requires-Dist: astropy>=5.3
Requires-Dist: awscli
Requires-Dist: boto3
Requires-Dist: earthaccess
Requires-Dist: eumdac
Requires-Dist: h5py
Requires-Dist: hatchling
Requires-Dist: netcdf4<1.7.0
Requires-Dist: numpy
Requires-Dist: pyerfa
Requires-Dist: pyhdf
Requires-Dist: sgp4
Requires-Dist: tqdm
Requires-Dist: xarray
